README.md
pyproject.toml
setup.cfg
setup.py
tushare/__init__.py
tushare/bond/__init__.py
tushare/bond/bonds.py
tushare/coins/__init__.py
tushare/coins/market.py
tushare/data/__init__.py
tushare/fund/__init__.py
tushare/fund/cons.py
tushare/fund/nav.py
tushare/futures/__init__.py
tushare/futures/cons.py
tushare/futures/domestic.py
tushare/futures/domestic_cons.py
tushare/futures/intlfutures.py
tushare/internet/__init__.py
tushare/internet/boxoffice.py
tushare/internet/caixinnews.py
tushare/internet/indexes.py
tushare/pro/__init__.py
tushare/pro/client.py
tushare/pro/data_pro.py
tushare/pro/llm.py
tushare/stock/__init__.py
tushare/stock/billboard.py
tushare/stock/classifying.py
tushare/stock/cons.py
tushare/stock/fundamental.py
tushare/stock/globals.py
tushare/stock/histroy_divide.py
tushare/stock/indictor.py
tushare/stock/macro.py
tushare/stock/macro_vars.py
tushare/stock/minsdata.py
tushare/stock/news_vars.py
tushare/stock/newsevent.py
tushare/stock/ref_vars.py
tushare/stock/reference.py
tushare/stock/rtq.py
tushare/stock/rtq_vars.py
tushare/stock/shibor.py
tushare/stock/trading.py
tushare/subs/__init__.py
tushare/subs/ht_subs/__init__.py
tushare/subs/ht_subs/covert.py
tushare/subs/ht_subs/subscribe.py
tushare/subs/model/__init__.py
tushare/subs/model/min.py
tushare/subs/model/tick.py
tushare/subs/tgw_subs/__init__.py
tushare/subs/tgw_subs/convert.py
tushare/subs/tgw_subs/login.py
tushare/subs/tgw_subs/subscribe.py
tushare/subs/ts_subs/__init__.py
tushare/subs/ts_subs/subscribe.py
tushare/trader/__init__.py
tushare/trader/trader.py
tushare/trader/utils.py
tushare/trader/vars.py
tushare/util/__init__.py
tushare/util/common.py
tushare/util/conns.py
tushare/util/dateu.py
tushare/util/form_date.py
tushare/util/format_stock_code.py
tushare/util/formula.py
tushare/util/mailmerge.py
tushare/util/netbase.py
tushare/util/store.py
tushare/util/upass.py
tushare/util/vars.py
tushare/util/verify_token.py
tushare/util/protobuf/__init__.py
tushare/util/protobuf/funcs.py
tushare_qpython.egg-info/PKG-INFO
tushare_qpython.egg-info/SOURCES.txt
tushare_qpython.egg-info/dependency_links.txt
tushare_qpython.egg-info/requires.txt
tushare_qpython.egg-info/top_level.txt