Metadata-Version: 2.4
Name: tushare-qpython
Version: 1.4.18
Summary: A utility for crawling historical and Real-time Quotes data of China stocks
Home-page: https://qpypi.qpython.org/project/tushare-qpython/
Author: The QPYPI Team
Author-email: qpypi@qpython.org
License: BSD
Keywords: Global Financial Data
Classifier: Intended Audience :: Developers
Classifier: Intended Audience :: Education
Classifier: Intended Audience :: Information Technology
Classifier: Intended Audience :: End Users/Desktop
Classifier: License :: OSI Approved :: Apache Software License
Classifier: Operating System :: Android
Classifier: Programming Language :: Python
Classifier: Programming Language :: Python :: 3.12
Classifier: Topic :: Software Development
Requires-Dist: pandas-aipy
Requires-Dist: requests
Requires-Dist: lxml-qpython
Requires-Dist: simplejson
Requires-Dist: bs4
Requires-Dist: websocket-client>=0.57.0
Requires-Dist: tqdm
Dynamic: author
Dynamic: author-email
Dynamic: classifier
Dynamic: description
Dynamic: description-content-type
Dynamic: home-page
Dynamic: keywords
Dynamic: license
Dynamic: requires-dist
Dynamic: summary
